polars_japanese-0.3.1.dist-info/METADATA
polars_japanese-0.3.1.dist-info/WHEEL
polars_japanese-0.3.1.dist-info/licenses/LICENSE
polars_japanese/__init__.py
polars_japanese/common.py
polars_japanese/datetime_util.py
polars_japanese/japanera_util.py
polars_japanese/jpholiday_util.py
polars_japanese/kanjize_util.py
polars_japanese/normalize_util.py
polars_japanese/plugin/__init__.py
polars_japanese/polars_japanese.abi3.so
polars_japanese/prefecture.py
polars_japanese-0.3.1.dist-info/RECORD
