Metadata-Version: 2.4
Name: polars-japanese
Version: 0.3.1
Requires-Dist: japanera>=2.1.2
Requires-Dist: jpholiday>=1.0.1
Requires-Dist: kanjize>=1.5.0
Requires-Dist: polars>=1.0.1
Requires-Dist: mkdocs>=1.6.1 ; extra == 'dev'
Requires-Dist: mkdocs-material>=9.6.12 ; extra == 'dev'
Requires-Dist: mkdocstrings[python]>=0.29.1 ; extra == 'dev'
Requires-Dist: mypy>=1.15.0 ; extra == 'dev'
Requires-Dist: pre-commit>=4.2.0 ; extra == 'dev'
Requires-Dist: pytest>=8.3.5 ; extra == 'dev'
Requires-Dist: pytest-cov>=6.1.1 ; extra == 'dev'
Requires-Dist: ruff>=0.11.5 ; extra == 'dev'
Requires-Dist: patchelf>=0.17.2.2 ; extra == 'dev'
Requires-Dist: twine>=6.1.0 ; extra == 'dev'
Provides-Extra: dev
License-File: LICENSE
Summary: polarsの日本向けのplugin library
Author-email: Jin Tanaka <jin3355.eco@gmail.com>
Requires-Python: >=3.10
Project-URL: Homepage, https://github.com/tanaka-jin/polars-japanese
Project-URL: Repository, https://github.com/tanaka-jin/polars-japanese
